{"name":"thisTestSkip","id":"edu.studentapp.junit.partTwo.DefferentTestOutCome:thisTestSkip","testCaseName":"edu.studentapp.junit.partTwo.DefferentTestOutCome","userStory":{"id":"edu.studentapp.junit.partTwo.DefferentTestOutCome","storyName":"Defferent test out come","storyClassName":"edu.studentapp.junit.partTwo.DefferentTestOutCome","path":"edu.studentapp.junit.partTwo","type":"feature"},"featureTag":{"name":"Part two/Defferent test out come","type":"feature"},"title":"This test skip","tags":[{"name":"Part two","type":"feature"},{"name":"Part two/Defferent test out come","type":"feature"}],"startTime":1606971738052,"duration":265,"projectKey":"","annotatedResult":"IGNORED","manual":false,"testSource":"JUnit","result":"IGNORED"}